freelanceapi/FreelanceExportData.py
freelanceapi/__init__.py
freelanceapi/_validator.py
freelanceapi/exception.py
freelanceapi/file_sections.py
freelanceapi/row_identificator.py
freelanceapi/sections/__SectionDict.py
freelanceapi/sections/__init__.py
freelanceapi/sections/area_dict.py
freelanceapi/sections/eam_dict.py
freelanceapi/sections/gwy_dict.py
freelanceapi/sections/hd_dict.py
freelanceapi/sections/hw2_dict.py
freelanceapi/sections/msr_dict.py
freelanceapi/sections/node_dict.py
freelanceapi/sections/para_dict.py
freelanceapi/sections/patchtable_dict.py
freelanceapi/sections/pbaum_dict.py
freelanceapi/sections/resourcen_dict.py
freelanceapi/utils.py
freelanceapi-0.2.4.dist-info/LICENSE
freelanceapi-0.2.4.dist-info/METADATA
freelanceapi-0.2.4.dist-info/WHEEL
freelanceapi-0.2.4.dist-info/RECORD
