Metadata-Version: 2.1
Name: FreelanceAPI
Version: 0.2.4
Summary: FreelanceAPI is a module for reading & evaluating export files from the Freelance control system.
Home-page: https://github.com/DarkJumper/FreelanceAPI
License: GNU
Author: Peter Schwarz
Author-email: p.schwarz1994@outlook.de
Requires-Python: >=3.10.0,<4.0.0
Classifier: License :: Other/Proprietary License
Classifier: Programming Language :: Python :: 3
Classifier: Programming Language :: Python :: 3.10
Classifier: Programming Language :: Python :: 3.11
Project-URL: Repository, https://github.com/DarkJumper/FreelanceAPI
